LT3OpenCorpora-0.2.1.data/scripts/lt_convert.py
LT3OpenCorpora-0.2.1.data/scripts/lt_plot.py
lt3opencorpora/__init__.py
lt3opencorpora/convert.py
lt3opencorpora/mapping.csv
lt3opencorpora/open_corpora_tagset.xml
LT3OpenCorpora-0.2.1.dist-info/LICENSE
LT3OpenCorpora-0.2.1.dist-info/METADATA
LT3OpenCorpora-0.2.1.dist-info/WHEEL
LT3OpenCorpora-0.2.1.dist-info/top_level.txt
LT3OpenCorpora-0.2.1.dist-info/RECORD
